[{"home":"Atlanta Falcons","away":"New Orleans Saints","link":"/games/55680/no-at-atl/","date":1354238400},{"home":"Buffalo Bills","away":"Jacksonville Jaguars","link":"/games/55681/jac-at-buf/","date":1354471200},{"home":"Chicago Bears","away":"Seattle Seahawks","link":"/games/55682/sea-at-chi/","date":1354471200},{"home":"Detroit Lions","away":"Indianapolis Colts","link":"/games/55683/ind-at-det/","date":1354471200},{"home":"Green Bay Packers","away":"Minnesota Vikings","link":"/games/55684/min-at-gb/","date":1354471200},{"home":"Kansas City Chiefs","away":"Carolina Panthers","link":"/games/55685/car-at-kc/","date":1354471200},{"home":"Miami Dolphins","away":"New England Patriots","link":"/games/55686/ne-at-mia/","date":1354471200},{"home":"New York Jets","away":"Arizona Cardinals","link":"/games/55687/ari-at-nyj/","date":1354471200},{"home":"St. Louis Rams","away":"San Francisco 49ers","link":"/games/55688/sf-at-stl/","date":1354471200},{"home":"Tennessee Titans","away":"Houston Texans","link":"/games/55689/hou-at-ten/","date":1354471200},{"home":"Denver Broncos","away":"Tampa Bay Buccaneers","link":"/games/55690/tb-at-den/","date":1354482300},{"home":"Baltimore Ravens","away":"Pittsburgh Steelers","link":"/games/55691/pit-at-bal/","date":1354483500},{"home":"Oakland Raiders","away":"Cleveland Browns","link":"/games/55692/cle-at-oak/","date":1354483500},{"home":"San Diego Chargers","away":"Cincinnati Bengals","link":"/games/55693/cin-at-sd/","date":1354483500},{"home":"Dallas Cowboys","away":"Philadelphia Eagles","link":"/games/55694/phi-at-dal/","date":1354497600},{"home":"Washington Redskins","away":"New York Giants","link":"/games/55695/nyg-at-was/","date":1354584600}]
